Workbook

Sheet README
A1: Risk register: template and sample (fictional company)
A2: Drafted by an AI (Claude) on 2026-10-16. Version 1.1. Not reviewed by a practitioner, certified security professional or auditor.
A3: Free sample. Not legal advice, not an audit, not a certification, and no guarantee of compliance or of any audit result. Not affiliated with or endorsed by NIST, Microsoft, Google or any standards body; Excel and Google Sheets are trademarks of their owners. Company, people and data are fictional; adapt everything to your real practice. References: NIST CSF 2.0 category IDs (NIST, February 2024); only IDs are used, all other wording is original. License: free for personal and internal business use. Do not sell or repackage it. Unmodified copies may be shared with this notice kept.
A5: How to use (5 steps)
A6: 1. Sheet 'Sample' shows a filled example for a 40-person firm. Sheet 'Blank' is yours. Yellow cells are inputs, grey cells are formulas (do not type over them).
A7: 2. List one risk per row. Score Likelihood and Impact as whole numbers 1 (very low) to 5 (very high). The sheet only accepts 1 to 5.
A8: 3. Score = Likelihood x Impact. Rating comes from the thresholds on the 'Settings' sheet (default High at 15 or more, Medium at 8 to 14, Low under 8). Change the thresholds on Settings only, and note why.
A9: 4. Pick one accountable person by role (an outside provider can help but should not be the only owner), one planned treatment, a status from the list, and the main NIST CSF 2.0 category ID from the list on the 'Lists' sheet.
A10: 5. Review High risks about every 3 months and the rest at least twice a year, and after any incident. Change status and date; do not delete old rows.
A11: Sheet notes: Blank holds 40 rows; to add more, copy the last row down (formulas, validation and formats come with it). Test cases are on the Tests sheet. Next review is a real date. Duplicate IDs turn orange and show '(duplicate)' in the ID column; fix them. If you add rows below the last row, extend the filter and the validation ranges by hand (Data > Filter). Whole numbers 1 to 5 only: a pasted 2.5, 0, -1 or text shows 'check input'. This file was built by a script (XlsxWriter 3.2.9), not saved from Excel.
A12: Any paid standard (for example ISO/IEC 27001) must be obtained by you; none is included or reproduced. Not affiliated with or endorsed by NIST, ISO/IEC, CIS, SANS, AICPA, Notion, Microsoft or Google.
A13: Limits: scores are judgment calls, not measurements. Treatments in the sample are illustrative. A register helps you decide and explain; it does not prove your controls work. Tested by script and by an automated run in desktop Excel 16 on Windows (formulas, validation, copy and reopen, 500 rows); not opened by a person. Not tested: Google Sheets, LibreOffice, Excel on the web, Excel's Accessibility Checker.

Sheet Settings
A1: Rating thresholds (edit here only)
A2: High if score is at least | B2: 15
A3: Medium if score is at least | B3: 8
A4: Otherwise Low. Rating text values are fixed: High, Medium, Low. High threshold must be larger than the Medium threshold.
A5: Lowest allowed score for Likelihood and Impact | B5: 1
A6: Highest allowed score for Likelihood and Impact | B6: 5
A7: Change the scale only if you also change the labels in the README. The Tests sheet assumes 1 to 5.

Sheet Tests
A1: Live tests (default Settings). Column H must say PASS.
A3: # | B3: Likelihood (E) | C3: Impact (F) | D3: Expected score | E3: Expected rating | F3: Actual score | G3: Actual rating | H3: Result | I3: Note
A4: 1 | B4: 1 | C4: 1 | D4: 1 | E4: Low | F4: =IF(OR(B4="",C4=""),"",IFERROR(IF(AND(ISNUMBER(B4),ISNUMBER(C4),B4=INT(B4),C4=INT(C4),B4>=Settings!$B$5,B4<=Settings!$B$6,C4>=Settings!$B$5,C4<=Settings!$B$6),B4*C4,"check input"),"check input")) -> 1 | G4: =IF(F4="","",IF(ISNUMBER(F4),IF(F4>=Settings!$B$2,"High",IF(F4>=Settings!$B$3,"Medium","Low")),"check input")) -> Low | H4: =IF(AND(F4&""=D4&"",G4&""=E4&""),"PASS","FAIL") -> PASS | I4: Lowest valid input
A5: 2 | B5: 5 | C5: 5 | D5: 25 | E5: High | F5: =IF(OR(B5="",C5=""),"",IFERROR(IF(AND(ISNUMBER(B5),ISNUMBER(C5),B5=INT(B5),C5=INT(C5),B5>=Settings!$B$5,B5<=Settings!$B$6,C5>=Settings!$B$5,C5<=Settings!$B$6),B5*C5,"check input"),"check input")) -> 25 | G5: =IF(F5="","",IF(ISNUMBER(F5),IF(F5>=Settings!$B$2,"High",IF(F5>=Settings!$B$3,"Medium","Low")),"check input")) -> High | H5: =IF(AND(F5&""=D5&"",G5&""=E5&""),"PASS","FAIL") -> PASS | I5: Highest valid input
A6: 3 | B6: 3 | C6: 5 | D6: 15 | E6: High | F6: =IF(OR(B6="",C6=""),"",IFERROR(IF(AND(ISNUMBER(B6),ISNUMBER(C6),B6=INT(B6),C6=INT(C6),B6>=Settings!$B$5,B6<=Settings!$B$6,C6>=Settings!$B$5,C6<=Settings!$B$6),B6*C6,"check input"),"check input")) -> 15 | G6: =IF(F6="","",IF(ISNUMBER(F6),IF(F6>=Settings!$B$2,"High",IF(F6>=Settings!$B$3,"Medium","Low")),"check input")) -> High | H6: =IF(AND(F6&""=D6&"",G6&""=E6&""),"PASS","FAIL") -> PASS | I6: On the High boundary (15)
A7: 4 | B7: 2 | C7: 7 | D7: check input | E7: check input | F7: =IF(OR(B7="",C7=""),"",IFERROR(IF(AND(ISNUMBER(B7),ISNUMBER(C7),B7=INT(B7),C7=INT(C7),B7>=Settings!$B$5,B7<=Settings!$B$6,C7>=Settings!$B$5,C7<=Settings!$B$6),B7*C7,"check input"),"check input")) -> check input | G7: =IF(F7="","",IF(ISNUMBER(F7),IF(F7>=Settings!$B$2,"High",IF(F7>=Settings!$B$3,"Medium","Low")),"check input")) -> check input | H7: =IF(AND(F7&""=D7&"",G7&""=E7&""),"PASS","FAIL") -> PASS | I7: Impact 7 is outside 1 to 5 (pasted values bypass validation): check input
A8: 5 | B8: 2 | C8: 4 | D8: 8 | E8: Medium | F8: =IF(OR(B8="",C8=""),"",IFERROR(IF(AND(ISNUMBER(B8),ISNUMBER(C8),B8=INT(B8),C8=INT(C8),B8>=Settings!$B$5,B8<=Settings!$B$6,C8>=Settings!$B$5,C8<=Settings!$B$6),B8*C8,"check input"),"check input")) -> 8 | G8: =IF(F8="","",IF(ISNUMBER(F8),IF(F8>=Settings!$B$2,"High",IF(F8>=Settings!$B$3,"Medium","Low")),"check input")) -> Medium | H8: =IF(AND(F8&""=D8&"",G8&""=E8&""),"PASS","FAIL") -> PASS | I8: On the Medium boundary (8)
A9: 6 | B9: 2 | C9: 3 | D9: 6 | E9: Low | F9: =IF(OR(B9="",C9=""),"",IFERROR(IF(AND(ISNUMBER(B9),ISNUMBER(C9),B9=INT(B9),C9=INT(C9),B9>=Settings!$B$5,B9<=Settings!$B$6,C9>=Settings!$B$5,C9<=Settings!$B$6),B9*C9,"check input"),"check input")) -> 6 | G9: =IF(F9="","",IF(ISNUMBER(F9),IF(F9>=Settings!$B$2,"High",IF(F9>=Settings!$B$3,"Medium","Low")),"check input")) -> Low | H9: =IF(AND(F9&""=D9&"",G9&""=E9&""),"PASS","FAIL") -> PASS | I9: Just under Medium (6, Low)
A10: 7 | B10: 4 | C10: 4 | D10: 16 | E10: High | F10: =IF(OR(B10="",C10=""),"",IFERROR(IF(AND(ISNUMBER(B10),ISNUMBER(C10),B10=INT(B10),C10=INT(C10),B10>=Settings!$B$5,B10<=Settings!$B$6,C10>=Settings!$B$5,C10<=Settings!$B$6),B10*C10,"check input"),"check input")) -> 16 | G10: =IF(F10="","",IF(ISNUMBER(F10),IF(F10>=Settings!$B$2,"High",IF(F10>=Settings!$B$3,"Medium","Low")),"check input")) -> High | H10: =IF(AND(F10&""=D10&"",G10&""=E10&""),"PASS","FAIL") -> PASS | I10: 16, High
A11: 8 | B11: 3 | C11: 4 | D11: 12 | E11: Medium | F11: =IF(OR(B11="",C11=""),"",IFERROR(IF(AND(ISNUMBER(B11),ISNUMBER(C11),B11=INT(B11),C11=INT(C11),B11>=Settings!$B$5,B11<=Settings!$B$6,C11>=Settings!$B$5,C11<=Settings!$B$6),B11*C11,"check input"),"check input")) -> 12 | G11: =IF(F11="","",IF(ISNUMBER(F11),IF(F11>=Settings!$B$2,"High",IF(F11>=Settings!$B$3,"Medium","Low")),"check input")) -> Medium | H11: =IF(AND(F11&""=D11&"",G11&""=E11&""),"PASS","FAIL") -> PASS | I11: 12, Medium
A12: 9 | C12: 3 | F12: =IF(OR(B12="",C12=""),"",IFERROR(IF(AND(ISNUMBER(B12),ISNUMBER(C12),B12=INT(B12),C12=INT(C12),B12>=Settings!$B$5,B12<=Settings!$B$6,C12>=Settings!$B$5,C12<=Settings!$B$6),B12*C12,"check input"),"check input")) | G12: =IF(F12="","",IF(ISNUMBER(F12),IF(F12>=Settings!$B$2,"High",IF(F12>=Settings!$B$3,"Medium","Low")),"check input")) | H12: =IF(AND(F12&""=D12&"",G12&""=E12&""),"PASS","FAIL") -> PASS | I12: Blank likelihood: empty result
A13: 10 | B13: 3 | F13: =IF(OR(B13="",C13=""),"",IFERROR(IF(AND(ISNUMBER(B13),ISNUMBER(C13),B13=INT(B13),C13=INT(C13),B13>=Settings!$B$5,B13<=Settings!$B$6,C13>=Settings!$B$5,C13<=Settings!$B$6),B13*C13,"check input"),"check input")) | G13: =IF(F13="","",IF(ISNUMBER(F13),IF(F13>=Settings!$B$2,"High",IF(F13>=Settings!$B$3,"Medium","Low")),"check input")) | H13: =IF(AND(F13&""=D13&"",G13&""=E13&""),"PASS","FAIL") -> PASS | I13: Blank impact: empty result
A14: 11 | B14: abc | C14: 3 | D14: check input | E14: check input | F14: =IF(OR(B14="",C14=""),"",IFERROR(IF(AND(ISNUMBER(B14),ISNUMBER(C14),B14=INT(B14),C14=INT(C14),B14>=Settings!$B$5,B14<=Settings!$B$6,C14>=Settings!$B$5,C14<=Settings!$B$6),B14*C14,"check input"),"check input")) -> check input | G14: =IF(F14="","",IF(ISNUMBER(F14),IF(F14>=Settings!$B$2,"High",IF(F14>=Settings!$B$3,"Medium","Low")),"check input")) -> check input | H14: =IF(AND(F14&""=D14&"",G14&""=E14&""),"PASS","FAIL") -> PASS | I14: Text pasted over a number: check input, no error value
A15: 12 | B15: 0 | C15: 3 | D15: check input | E15: check input | F15: =IF(OR(B15="",C15=""),"",IFERROR(IF(AND(ISNUMBER(B15),ISNUMBER(C15),B15=INT(B15),C15=INT(C15),B15>=Settings!$B$5,B15<=Settings!$B$6,C15>=Settings!$B$5,C15<=Settings!$B$6),B15*C15,"check input"),"check input")) -> check input | G15: =IF(F15="","",IF(ISNUMBER(F15),IF(F15>=Settings!$B$2,"High",IF(F15>=Settings!$B$3,"Medium","Low")),"check input")) -> check input | H15: =IF(AND(F15&""=D15&"",G15&""=E15&""),"PASS","FAIL") -> PASS | I15: Zero pasted: check input
A16: 13 | B16: 2.5 | C16: 3 | D16: check input | E16: check input | F16: =IF(OR(B16="",C16=""),"",IFERROR(IF(AND(ISNUMBER(B16),ISNUMBER(C16),B16=INT(B16),C16=INT(C16),B16>=Settings!$B$5,B16<=Settings!$B$6,C16>=Settings!$B$5,C16<=Settings!$B$6),B16*C16,"check input"),"check input")) -> check input | G16: =IF(F16="","",IF(ISNUMBER(F16),IF(F16>=Settings!$B$2,"High",IF(F16>=Settings!$B$3,"Medium","Low")),"check input")) -> check input | H16: =IF(AND(F16&""=D16&"",G16&""=E16&""),"PASS","FAIL") -> PASS | I16: Decimal pasted: check input
A17: 14 | B17: -1 | C17: 3 | D17: check input | E17: check input | F17: =IF(OR(B17="",C17=""),"",IFERROR(IF(AND(ISNUMBER(B17),ISNUMBER(C17),B17=INT(B17),C17=INT(C17),B17>=Settings!$B$5,B17<=Settings!$B$6,C17>=Settings!$B$5,C17<=Settings!$B$6),B17*C17,"check input"),"check input")) -> check input | G17: =IF(F17="","",IF(ISNUMBER(F17),IF(F17>=Settings!$B$2,"High",IF(F17>=Settings!$B$3,"Medium","Low")),"check input")) -> check input | H17: =IF(AND(F17&""=D17&"",G17&""=E17&""),"PASS","FAIL") -> PASS | I17: Negative pasted: check input
A19: Duplicate ID test (the registers highlight duplicates in orange with a text cue; this shows the same check)
A20: # | B20: ID entered | C20: Expected | D20: Actual | E20: Result
A21: 15 | B21: R01 | C21: DUPLICATE | D21: =IF(COUNTIF($B$21:$B$23,B21)>1,"DUPLICATE","ok") -> DUPLICATE | E21: =IF(C21=D21,"PASS","FAIL") -> PASS
A22: 16 | B22: R01 | C22: DUPLICATE | D22: =IF(COUNTIF($B$21:$B$23,B22)>1,"DUPLICATE","ok") -> DUPLICATE | E22: =IF(C22=D22,"PASS","FAIL") -> PASS
A23: 17 | B23: R02 | C23: ok | D23: =IF(COUNTIF($B$21:$B$23,B23)>1,"DUPLICATE","ok") -> ok | E23: =IF(C23=D23,"PASS","FAIL") -> PASS
A25: Cached results were computed by a script from the same logic. An automated script opened this file in desktop Excel 16 on Windows and all Results said PASS. No person has opened it, and Google Sheets and LibreOffice are untested; open this sheet and confirm every Result says PASS.

Sheet Lists
A1: CSF 2.0 category | B1: Status
A2: GV.OC | B2: Open
A3: GV.RM | B3: In progress
A4: GV.RR | B4: Done
A5: GV.PO | B5: Accepted
A6: GV.OV
A7: GV.SC
A8: ID.AM
A9: ID.RA
A10: ID.IM
A11: PR.AA
A12: PR.AT
A13: PR.DS
A14: PR.PS
A15: PR.IR
A16: DE.CM
A17: DE.AE
... A23: RC.CO

Sheet Sample
A1: ID | B1: Risk (what could go wrong) | C1: Asset | D1: CSF 2.0 category | E1: Likelihood (1-5) | F1: Impact (1-5) | G1: Score (L x I) | H1: Rating | I1: Owner (role) | J1: Planned treatment | K1: Status | L1: Next review
A2: R01 | B2: Staff enter passwords on a phishing page, giving an attacker mailbox access | C2: Email accounts | D2: PR.AA | E2: 4 | F2: 4 | G2: =IF(OR(E2="",F2=""),"",IFERROR(IF(AND(ISNUMBER(E2),ISNUMBER(F2),E2=INT(E2),F2=INT(F2),E2>=Settings!$B$5,E2<=Settings!$B$6,F2>=Settings!$B$5,F2<=Settings!$B$6),E2*F2,"check input"),"check input")) -> 16 | H2: =IF(G2="","",IF(ISNUMBER(G2),IF(G2>=Settings!$B$2,"High",IF(G2>=Settings!$B$3,"Medium","Low")),"check input")) -> High | I2: Office manager | J2: Require multi-factor sign-in for all mail accounts; phishing awareness session twice a year; report-this-email button | K2: In progress | L2: 46371
A3: R08 | B3: No one knows who leads during an incident | C3: Incident response | D3: GV.RR | E3: 4 | F3: 4 | G3: =IF(OR(E3="",F3=""),"",IFERROR(IF(AND(ISNUMBER(E3),ISNUMBER(F3),E3=INT(E3),F3=INT(F3),E3>=Settings!$B$5,E3<=Settings!$B$6,F3>=Settings!$B$5,F3<=Settings!$B$6),E3*F3,"check input"),"check input")) -> 16 | H3: =IF(G3="","",IF(ISNUMBER(G3),IF(G3>=Settings!$B$2,"High",IF(G3>=Settings!$B$3,"Medium","Low")),"check input")) -> High | I3: Managing partner | J3: Adopt a written first-hour checklist; run a 30 minute tabletop each year | K3: In progress | L3: 46371
A4: R02 | B4: Ransomware encrypts the shared file server before the tax deadline | C4: File server, client files | D4: PR.DS | E4: 3 | F4: 5 | G4: =IF(OR(E4="",F4=""),"",IFERROR(IF(AND(ISNUMBER(E4),ISNUMBER(F4),E4=INT(E4),F4=INT(F4),E4>=Settings!$B$5,E4<=Settings!$B$6,F4>=Settings!$B$5,F4<=Settings!$B$6),E4*F4,"check input"),"check input")) -> 15 | H4: =IF(G4="","",IF(ISNUMBER(G4),IF(G4>=Settings!$B$2,"High",IF(G4>=Settings!$B$3,"Medium","Low")),"check input")) -> High | I4: Office manager with IT provider | J4: Keep one offline or immutable backup copy; test a restore each quarter; limit who can write to shared folders | K4: In progress | L4: 46371
A5: R03 | B5: Laptop with client tax data is lost or stolen | C5: Staff laptops | D5: PR.DS | E5: 3 | F5: 4 | G5: =IF(OR(E5="",F5=""),"",IFERROR(IF(AND(ISNUMBER(E5),ISNUMBER(F5),E5=INT(E5),F5=INT(F5),E5>=Settings!$B$5,E5<=Settings!$B$6,F5>=Settings!$B$5,F5<=Settings!$B$6),E5*F5,"check input"),"check input")) -> 12 | H5: =IF(G5="","",IF(ISNUMBER(G5),IF(G5>=Settings!$B$2,"High",IF(G5>=Settings!$B$3,"Medium","Low")),"check input")) -> Medium | I5: Office manager with IT provider | J5: Full-disk encryption on every laptop; remote wipe; no local storage of client files | K5: Open | L5: 46402
A6: R06 | B6: Unpatched software on staff computers is exploited | C6: Workstations | D6: PR.PS | E6: 3 | F6: 4 | G6: =IF(OR(E6="",F6=""),"",IFERROR(IF(AND(ISNUMBER(E6),ISNUMBER(F6),E6=INT(E6),F6=INT(F6),E6>=Settings!$B$5,E6<=Settings!$B$6,F6>=Settings!$B$5,F6<=Settings!$B$6),E6*F6,"check input"),"check input")) -> 12 | H6: =IF(G6="","",IF(ISNUMBER(G6),IF(G6>=Settings!$B$2,"High",IF(G6>=Settings!$B$3,"Medium","Low")),"check input")) -> Medium | I6: Office manager with IT provider | J6: Turn on automatic updates; monthly report of machines more than 30 days behind | K6: In progress | L6: 46402
A7: R07 | B7: Client data emailed to the wrong recipient | C7: Client records | D7: PR.DS | E7: 4 | F7: 3 | G7: =IF(OR(E7="",F7=""),"",IFERROR(IF(AND(ISNUMBER(E7),ISNUMBER(F7),E7=INT(E7),F7=INT(F7),E7>=Settings!$B$5,E7<=Settings!$B$6,F7>=Settings!$B$5,F7<=Settings!$B$6),E7*F7,"check input"),"check input")) -> 12 | H7: =IF(G7="","",IF(ISNUMBER(G7),IF(G7>=Settings!$B$2,"High",IF(G7>=Settings!$B$3,"Medium","Low")),"check input")) -> Medium | I7: Practice lead | J7: Use the secure client portal for tax documents; delay-send on outgoing mail for 60 seconds | K7: Open | L7: 46402
A8: R11 | B8: No inventory of systems and cloud services in use | C8: All assets | D8: ID.AM | E8: 4 | F8: 3 | G8: =IF(OR(E8="",F8=""),"",IFERROR(IF(AND(ISNUMBER(E8),ISNUMBER(F8),E8=INT(E8),F8=INT(F8),E8>=Settings!$B$5,E8<=Settings!$B$6,F8>=Settings!$B$5,F8<=Settings!$B$6),E8*F8,"check input"),"check input")) -> 12 | H8: =IF(G8="","",IF(ISNUMBER(G8),IF(G8>=Settings!$B$2,"High",IF(G8>=Settings!$B$3,"Medium","Low")),"check input")) -> Medium | I8: Office manager | J8: Build a simple list of systems, owners and where client data lives; review twice a year | K8: Open | L8: 46402
A9: R12 | B9: Suspicious sign-ins go unnoticed for days | C9: Email and cloud accounts | D9: DE.CM | E9: 3 | F9: 4 | G9: =IF(OR(E9="",F9=""),"",IFERROR(IF(AND(ISNUMBER(E9),ISNUMBER(F9),E9=INT(E9),F9=INT(F9),E9>=Settings!$B$5,E9<=Settings!$B$6,F9>=Settings!$B$5,F9<=Settings!$B$6),E9*F9,"check input"),"check input")) -> 12 | H9: =IF(G9="","",IF(ISNUMBER(G9),IF(G9>=Settings!$B$2,"High",IF(G9>=Settings!$B$3,"Medium","Low")),"check input")) -> Medium | I9: Office manager with IT provider | J9: Turn on sign-in alerts for unusual location; one person receives them | K9: Open | L9: 46402
A10: R05 | B10: IT provider has broad admin access and suffers its own breach | C10: Third-party IT provider | D10: GV.SC | E10: 2 | F10: 5 | G10: =IF(OR(E10="",F10=""),"",IFERROR(IF(AND(ISNUMBER(E10),ISNUMBER(F10),E10=INT(E10),F10=INT(F10),E10>=Settings!$B$5,E10<=Settings!$B$6,F10>=Settings!$B$5,F10<=Settings!$B$6),E10*F10,"check input"),"check input")) -> 10 | H10: =IF(G10="","",IF(ISNUMBER(G10),IF(G10>=Settings!$B$2,"High",IF(G10>=Settings!$B$3,"Medium","Low")),"check input")) -> Medium | I10: Managing partner | J10: Ask for the provider's security practices in writing; require separate admin accounts with multi-factor; put breach-notice time in the contract | K10: Open | L10: 46402
A11: R04 | B11: A departed employee's accounts stay active | C11: User accounts | D11: PR.AA | E11: 3 | F11: 3 | G11: =IF(OR(E11="",F11=""),"",IFERROR(IF(AND(ISNUMBER(E11),ISNUMBER(F11),E11=INT(E11),F11=INT(F11),E11>=Settings!$B$5,E11<=Settings!$B$6,F11>=Settings!$B$5,F11<=Settings!$B$6),E11*F11,"check input"),"check input")) -> 9 | H11: =IF(G11="","",IF(ISNUMBER(G11),IF(G11>=Settings!$B$2,"High",IF(G11>=Settings!$B$3,"Medium","Low")),"check input")) -> Medium | I11: HR lead | J11: Same-day offboarding checklist; monthly list of active accounts compared to payroll | K11: Open | L11: 46402
A12: R13 | B12: Remote staff use personal devices without protection | C12: Personal devices | D12: PR.PS | E12: 3 | F12: 3 | G12: =IF(OR(E12="",F12=""),"",IFERROR(IF(AND(ISNUMBER(E12),ISNUMBER(F12),E12=INT(E12),F12=INT(F12),E12>=Settings!$B$5,E12<=Settings!$B$6,F12>=Settings!$B$5,F12<=Settings!$B$6),E12*F12,"check input"),"check input")) -> 9 | H12: =IF(G12="","",IF(ISNUMBER(G12),IF(G12>=Settings!$B$2,"High",IF(G12>=Settings!$B$3,"Medium","Low")),"check input")) -> Medium | I12: Practice lead | J12: Written rule on personal devices; require screen lock and updates; prefer company laptops for client work | K12: Open | L12: 46402
A13: R09 | B13: Cyber insurance does not cover a payment-redirect fraud | C13: Insurance | D13: GV.RM | E13: 2 | F13: 4 | G13: =IF(OR(E13="",F13=""),"",IFERROR(IF(AND(ISNUMBER(E13),ISNUMBER(F13),E13=INT(E13),F13=INT(F13),E13>=Settings!$B$5,E13<=Settings!$B$6,F13>=Settings!$B$5,F13<=Settings!$B$6),E13*F13,"check input"),"check input")) -> 8 | H13: =IF(G13="","",IF(ISNUMBER(G13),IF(G13>=Settings!$B$2,"High",IF(G13>=Settings!$B$3,"Medium","Low")),"check input")) -> Medium | I13: Managing partner | J13: Read the policy exclusions with the broker; ask in writing about social engineering cover | K13: Open | L13: 46402
... A15: R10 | B15: Guest Wi-Fi shares a network with office computers | C15: Office network | D15: PR.IR | E15: 2 | F15: 3 | G15: =IF(OR(E15="",F15=""),"",IFERROR(IF(AND(ISNUMBER(E15),ISNUMBER(F15),E15=INT(E15),F15=INT(F15),E15>=Settings!$B$5,E15<=Settings!$B$6,F15>=Settings!$B$5,F15<=Settings!$B$6),E15*F15,"check input"),"check input")) -> 6 | H15: =IF(G15="","",IF(ISNUMBER(G15),IF(G15>=Settings!$B$2,"High",IF(G15>=Settings!$B$3,"Medium","Low")),"check input")) -> Low | I15: Office manager with IT provider | J15: Separate guest network; change the router admin password | K15: Open | L15: 46492

Sheet Blank
A1: ID | B1: Risk (what could go wrong) | C1: Asset | D1: CSF 2.0 category | E1: Likelihood (1-5) | F1: Impact (1-5) | G1: Score (L x I) | H1: Rating | I1: Owner (role) | J1: Planned treatment | K1: Status | L1: Next review
G2: =IF(OR(E2="",F2=""),"",IFERROR(IF(AND(ISNUMBER(E2),ISNUMBER(F2),E2=INT(E2),F2=INT(F2),E2>=Settings!$B$5,E2<=Settings!$B$6,F2>=Settings!$B$5,F2<=Settings!$B$6),E2*F2,"check input"),"check input")) | H2: =IF(G2="","",IF(ISNUMBER(G2),IF(G2>=Settings!$B$2,"High",IF(G2>=Settings!$B$3,"Medium","Low")),"check input"))
G3: =IF(OR(E3="",F3=""),"",IFERROR(IF(AND(ISNUMBER(E3),ISNUMBER(F3),E3=INT(E3),F3=INT(F3),E3>=Settings!$B$5,E3<=Settings!$B$6,F3>=Settings!$B$5,F3<=Settings!$B$6),E3*F3,"check input"),"check input")) | H3: =IF(G3="","",IF(ISNUMBER(G3),IF(G3>=Settings!$B$2,"High",IF(G3>=Settings!$B$3,"Medium","Low")),"check input"))
G4: =IF(OR(E4="",F4=""),"",IFERROR(IF(AND(ISNUMBER(E4),ISNUMBER(F4),E4=INT(E4),F4=INT(F4),E4>=Settings!$B$5,E4<=Settings!$B$6,F4>=Settings!$B$5,F4<=Settings!$B$6),E4*F4,"check input"),"check input")) | H4: =IF(G4="","",IF(ISNUMBER(G4),IF(G4>=Settings!$B$2,"High",IF(G4>=Settings!$B$3,"Medium","Low")),"check input"))
G5: =IF(OR(E5="",F5=""),"",IFERROR(IF(AND(ISNUMBER(E5),ISNUMBER(F5),E5=INT(E5),F5=INT(F5),E5>=Settings!$B$5,E5<=Settings!$B$6,F5>=Settings!$B$5,F5<=Settings!$B$6),E5*F5,"check input"),"check input")) | H5: =IF(G5="","",IF(ISNUMBER(G5),IF(G5>=Settings!$B$2,"High",IF(G5>=Settings!$B$3,"Medium","Low")),"check input"))
G6: =IF(OR(E6="",F6=""),"",IFERROR(IF(AND(ISNUMBER(E6),ISNUMBER(F6),E6=INT(E6),F6=INT(F6),E6>=Settings!$B$5,E6<=Settings!$B$6,F6>=Settings!$B$5,F6<=Settings!$B$6),E6*F6,"check input"),"check input")) | H6: =IF(G6="","",IF(ISNUMBER(G6),IF(G6>=Settings!$B$2,"High",IF(G6>=Settings!$B$3,"Medium","Low")),"check input"))
G7: =IF(OR(E7="",F7=""),"",IFERROR(IF(AND(ISNUMBER(E7),ISNUMBER(F7),E7=INT(E7),F7=INT(F7),E7>=Settings!$B$5,E7<=Settings!$B$6,F7>=Settings!$B$5,F7<=Settings!$B$6),E7*F7,"check input"),"check input")) | H7: =IF(G7="","",IF(ISNUMBER(G7),IF(G7>=Settings!$B$2,"High",IF(G7>=Settings!$B$3,"Medium","Low")),"check input"))
G8: =IF(OR(E8="",F8=""),"",IFERROR(IF(AND(ISNUMBER(E8),ISNUMBER(F8),E8=INT(E8),F8=INT(F8),E8>=Settings!$B$5,E8<=Settings!$B$6,F8>=Settings!$B$5,F8<=Settings!$B$6),E8*F8,"check input"),"check input")) | H8: =IF(G8="","",IF(ISNUMBER(G8),IF(G8>=Settings!$B$2,"High",IF(G8>=Settings!$B$3,"Medium","Low")),"check input"))
G9: =IF(OR(E9="",F9=""),"",IFERROR(IF(AND(ISNUMBER(E9),ISNUMBER(F9),E9=INT(E9),F9=INT(F9),E9>=Settings!$B$5,E9<=Settings!$B$6,F9>=Settings!$B$5,F9<=Settings!$B$6),E9*F9,"check input"),"check input")) | H9: =IF(G9="","",IF(ISNUMBER(G9),IF(G9>=Settings!$B$2,"High",IF(G9>=Settings!$B$3,"Medium","Low")),"check input"))
G10: =IF(OR(E10="",F10=""),"",IFERROR(IF(AND(ISNUMBER(E10),ISNUMBER(F10),E10=INT(E10),F10=INT(F10),E10>=Settings!$B$5,E10<=Settings!$B$6,F10>=Settings!$B$5,F10<=Settings!$B$6),E10*F10,"check input"),"check input")) | H10: =IF(G10="","",IF(ISNUMBER(G10),IF(G10>=Settings!$B$2,"High",IF(G10>=Settings!$B$3,"Medium","Low")),"check input"))
G11: =IF(OR(E11="",F11=""),"",IFERROR(IF(AND(ISNUMBER(E11),ISNUMBER(F11),E11=INT(E11),F11=INT(F11),E11>=Settings!$B$5,E11<=Settings!$B$6,F11>=Settings!$B$5,F11<=Settings!$B$6),E11*F11,"check input"),"check input")) | H11: =IF(G11="","",IF(ISNUMBER(G11),IF(G11>=Settings!$B$2,"High",IF(G11>=Settings!$B$3,"Medium","Low")),"check input"))
G12: =IF(OR(E12="",F12=""),"",IFERROR(IF(AND(ISNUMBER(E12),ISNUMBER(F12),E12=INT(E12),F12=INT(F12),E12>=Settings!$B$5,E12<=Settings!$B$6,F12>=Settings!$B$5,F12<=Settings!$B$6),E12*F12,"check input"),"check input")) | H12: =IF(G12="","",IF(ISNUMBER(G12),IF(G12>=Settings!$B$2,"High",IF(G12>=Settings!$B$3,"Medium","Low")),"check input"))
G13: =IF(OR(E13="",F13=""),"",IFERROR(IF(AND(ISNUMBER(E13),ISNUMBER(F13),E13=INT(E13),F13=INT(F13),E13>=Settings!$B$5,E13<=Settings!$B$6,F13>=Settings!$B$5,F13<=Settings!$B$6),E13*F13,"check input"),"check input")) | H13: =IF(G13="","",IF(ISNUMBER(G13),IF(G13>=Settings!$B$2,"High",IF(G13>=Settings!$B$3,"Medium","Low")),"check input"))
... G41: =IF(OR(E41="",F41=""),"",IFERROR(IF(AND(ISNUMBER(E41),ISNUMBER(F41),E41=INT(E41),F41=INT(F41),E41>=Settings!$B$5,E41<=Settings!$B$6,F41>=Settings!$B$5,F41<=Settings!$B$6),E41*F41,"check input"),"check input")) | H41: =IF(G41="","",IF(ISNUMBER(G41),IF(G41>=Settings!$B$2,"High",IF(G41>=Settings!$B$3,"Medium","Low")),"check input"))
